calibrade/__init__.py
calibrade/constants.py
calibrade/opencv_intro.py
calibrade/prune.py
calibrade-0.1.1.dist-info/LICENSE
calibrade-0.1.1.dist-info/WHEEL
calibrade-0.1.1.dist-info/METADATA
calibrade-0.1.1.dist-info/RECORD
