Metadata-Version: 2.1
Name: calibrade
Version: 0.1.1
Summary: A toolbox for end-to-end camera calibration with minimal pain.
License: MIT
Author: Aarrushi Shandilya
Requires-Python: >=3.8,<3.11
Classifier: License :: OSI Approved :: MIT License
Classifier: Programming Language :: Python :: 3
Classifier: Programming Language :: Python :: 3.10
Classifier: Programming Language :: Python :: 3.8
Classifier: Programming Language :: Python :: 3.9
Requires-Dist: matplotlib (>=3.4.3,<4.0.0)
Requires-Dist: numpy (>=1.21.3,<2.0.0)
Requires-Dist: opencv-python (>=4.5.4,<5.0.0)
